sparrow_datums/__init__.py
sparrow_datums/chunk.py
sparrow_datums/chunk_test.py
sparrow_datums/chunk_types.py
sparrow_datums/chunk_types_test.py
sparrow_datums/exceptions.py
sparrow_datums/boxes/__init__.py
sparrow_datums/boxes/augmented_boxes.py
sparrow_datums/boxes/augmented_boxes_test.py
sparrow_datums/boxes/boxes.py
sparrow_datums/boxes/boxes_test.py
sparrow_datums/boxes/frame_augmented_boxes.py
sparrow_datums/boxes/frame_augmented_boxes_test.py
sparrow_datums/boxes/frame_boxes.py
sparrow_datums/boxes/frame_boxes_test.py
sparrow_datums/boxes/iou.py
sparrow_datums/boxes/iou_test.py
sparrow_datums/boxes/nms.py
sparrow_datums/boxes/nms_test.py
sparrow_datums/boxes/single_augmented_box.py
sparrow_datums/boxes/single_augmented_box_test.py
sparrow_datums/boxes/single_box.py
sparrow_datums/boxes/single_box_test.py
sparrow_datums/keypoints/__init__.py
sparrow_datums/keypoints/keypoints.py
sparrow_datums/keypoints/keypoints_test.py
sparrow_datums/stream/__init__.py
sparrow_datums/stream/reader.py
sparrow_datums/stream/reader_test.py
sparrow_datums/stream/stream_types.py
sparrow_datums/stream/stream_types_test.py
sparrow_datums/stream/writer.py
sparrow_datums/stream/writer_test.py
sparrow_datums/tracking/__init__.py
sparrow_datums/tracking/augmented_box_tracking.py
sparrow_datums/tracking/augmented_box_tracking_test.py
sparrow_datums/tracking/box_tracking.py
sparrow_datums/tracking/box_tracking_test.py
sparrow_datums/tracking/tracking.py
sparrow_datums/tracking/tracking_test.py
sparrow_datums-0.11.2.dist-info/licenses/LICENSE
sparrow_datums-0.11.2.dist-info/METADATA
sparrow_datums-0.11.2.dist-info/WHEEL
sparrow_datums-0.11.2.dist-info/top_level.txt
sparrow_datums-0.11.2.dist-info/RECORD
