Metadata-Version: 2.4
Name: sparrow-datums
Version: 0.11.2
Author-email: Sparrow Computing <ben@sparrow.dev>
Requires-Python: >=3.12
License-File: LICENSE
Requires-Dist: fire
Requires-Dist: numpy
Requires-Dist: xmltodict
Provides-Extra: dev
Requires-Dist: jupyter; extra == "dev"
Requires-Dist: pytest; extra == "dev"
Requires-Dist: pytest-cov; extra == "dev"
Requires-Dist: uv; extra == "dev"
Dynamic: license-file
